ryght/__init__.py
ryght/clients/__init__.py
ryght/clients/api.py
ryght/clients/user.py
ryght/configs/__init__.py
ryght/configs/api_config.py
ryght/configs/api_endpoints.yaml
ryght/interface/__init__.py
ryght/interface/api.py
ryght/interface/client.py
ryght/managers/__init__.py
ryght/managers/collections.py
ryght/managers/tokens.py
ryght/models/__init__.py
ryght/models/data_models.py
ryght/requests/__init__.py
ryght/requests/http_requestor.py
ryght/utils/__init__.py
ryght_platform_sdk-0.4.1.dist-info/METADATA
ryght_platform_sdk-0.4.1.dist-info/WHEEL
ryght_platform_sdk-0.4.1.dist-info/RECORD
